Metadata-Version: 2.3
Name: tech-mcp-demo-pypi
Version: 0.1.0
Summary: Add your description here
Author: 顾苗苗
Author-email: 顾苗苗 <gumiaomiao@mininglamp.com>
Requires-Dist: mcp[cli]>=1.23.2
Requires-Python: >=3.10
